errors/__init__.py
errors/base.py
flexagent-0.1.0.dist-info/licenses/LICENSE
strategies/__init__.py
strategies/base.py
strategies/gemini.py
tools/__init__.py
tools/base.py
tools/registry.py
types/__init__.py
types/models.py
utils/__init__.py
utils/logger.py
flexagent-0.1.0.dist-info/METADATA
flexagent-0.1.0.dist-info/WHEEL
flexagent-0.1.0.dist-info/top_level.txt
flexagent-0.1.0.dist-info/RECORD
