Metadata-Version: 2.4
Name: flexAgent
Version: 0.1.0
Summary: Um orquestrador de agentes flexível
Author-email: fernando <fernando.santos@passabot.com>
License-Expression: MIT
Requires-Python: >=3.9
License-File: LICENSE
Dynamic: license-file
